pwq_qr_gen_4/PWQ_QR_Gen_4.py
pwq_qr_gen_4/__init__.py
pwq_qr_gen_4-4.0.44.dist-info/METADATA
pwq_qr_gen_4-4.0.44.dist-info/WHEEL
pwq_qr_gen_4-4.0.44.dist-info/top_level.txt
pwq_qr_gen_4-4.0.44.dist-info/RECORD
