Metadata-Version: 2.4
Name: pwq_qr_gen_4
Version: 4.0.44
Summary: A fully customizable QR code generator with support for colors, logos, and links.
Home-page: https://github.com/pawlexcode95/PWQ-QR-Gen-4-A-Fully-Customizable-QR-Code-Generator
Author: pawlexcode95
Project-URL: Homepage, https://github.com/pawlexcode95/PWQ-QR-Gen-4-A-Fully-Customizable-QR-Code-Generator
Project-URL: Script, https://github.com/pawlexcode95/PWQ-QR-Gen-4-A-Fully-Customizable-QR-Code-Generator/blob/main/PWQ_QR_Gen_4.py
Project-URL: Issues, https://github.com/pawlexcode95/PWQ-QR-Gen-4-A-Fully-Customizable-QR-Code-Generator/issues
Requires-Python: >=3.11
Requires-Dist: pillow
Dynamic: home-page
Dynamic: requires-python
